<?xml version="1.0" encoding="utf-8"?>
<clothing-items>
 <clothing>
  <id>
   408983042
  </id>
  <name>
   Addidas Shirt V-6609
  </name>
  <category>
   Shirt
  </category>
  <size>
   L
  </size>
  <color>
   Зеленый
  </color>
  <material>
   Шелк
  </material>
  <price>
   424481
  </price>
  <rating>
   1.06
  </rating>
  <reviews>
   737945
  </reviews>
  <new>
   +
  </new>
 </clothing>
 <clothing>
  <id>
   729430355
  </id>
  <name>
   New Balance T-shirt N-1260
  </name>
  <category>
   T-shirt
  </category>
  <size>
   L
  </size>
  <color>
   Синий
  </color>
  <material>
   Хлопок
  </material>
  <price>
   383202
  </price>
  <rating>
   1.04
  </rating>
  <reviews>
   873643
  </reviews>
  <new>
   -
  </new>
  <exclusive>
   yes
  </exclusive>
  <sporty>
   yes
  </sporty>
 </clothing>
 <clothing>
  <id>
   552422073
  </id>
  <name>
   Converse Shoes X-3991
  </name>
  <category>
   Shoes
  </category>
  <size>
   XXL
  </size>
  <color>
   Синий
  </color>
  <material>
   Кожа
  </material>
  <price>
   148765
  </price>
  <rating>
   2.51
  </rating>
  <reviews>
   138526
  </reviews>
  <new>
   -
  </new>
 </clothing>
 <clothing>
  <id>
   590539382
  </id>
  <name>
   Adidas Pants A-2757
  </name>
  <category>
   Pants
  </category>
  <size>
   M
  </size>
  <color>
   Красный
  </color>
  <material>
   Шерсть
  </material>
  <price>
   137138
  </price>
  <rating>
   2.27
  </rating>
  <reviews>
   221891
  </reviews>
  <exclusive>
   no
  </exclusive>
 </clothing>
 <clothing>
  <id>
   652588197
  </id>
  <name>
   Puma Gloves G-5615
  </name>
  <category>
   Gloves
  </category>
  <size>
   L
  </size>
  <color>
   Красный
  </color>
  <material>
   Вискоза
  </material>
  <price>
   216368
  </price>
  <rating>
   1.29
  </rating>
  <reviews>
   800951
  </reviews>
  <new>
   -
  </new>
 </clothing>
 <clothing>
  <id>
   355681937
  </id>
  <name>
   Ellesse Belts E-8715
  </name>
  <category>
   Belts
  </category>
  <size>
   XL
  </size>
  <color>
   Оранжевый
  </color>
  <material>
   Шерсть
  </material>
  <price>
   304242
  </price>
  <rating>
   3.26
  </rating>
  <reviews>
   230734
  </reviews>
 </clothing>
 <clothing>
  <id>
   790764227
  </id>
  <name>
   Fila Sweater G-1993
  </name>
  <category>
   Sweater
  </category>
  <size>
   M
  </size>
  <color>
   Фиолетовый
  </color>
  <material>
   Полиэстер
  </material>
  <price>
   141990
  </price>
  <rating>
   4.84
  </rating>
  <reviews>
   894019
  </reviews>
  <new>
   +
  </new>
  <exclusive>
   yes
  </exclusive>
  <sporty>
   no
  </sporty>
 </clothing>
 <clothing>
  <id>
   502334342
  </id>
  <name>
   Puma Pants A-9477
  </name>
  <category>
   Pants
  </category>
  <size>
   L
  </size>
  <color>
   Оранжевый
  </color>
  <material>
   Вискоза
  </material>
  <price>
   555264
  </price>
  <rating>
   1.81
  </rating>
  <reviews>
   398359
  </reviews>
  <new>
   -
  </new>
 </clothing>
 <clothing>
  <id>
   195007073
  </id>
  <name>
   Vans Socks W-6708
  </name>
  <category>
   Socks
  </category>
  <size>
   XL
  </size>
  <color>
   Голубой
  </color>
  <material>
   Лен
  </material>
  <price>
   661468
  </price>
  <rating>
   4.15
  </rating>
  <reviews>
   430402
  </reviews>
  <new>
   +
  </new>
  <sporty>
   no
  </sporty>
 </clothing>
 <clothing>
  <id>
   242034307
  </id>
  <name>
   Ellesse Gloves M-2525
  </name>
  <category>
   Gloves
  </category>
  <size>
   L
  </size>
  <color>
   Оранжевый
  </color>
  <material>
   Шерсть
  </material>
  <price>
   801084
  </price>
  <rating>
   4.63
  </rating>
  <reviews>
   504820
  </reviews>
  <exclusive>
   no
  </exclusive>
 </clothing>
 <clothing>
  <id>
   769417604
  </id>
  <name>
   Lacoste Hat U-8954
  </name>
  <category>
   Hat
  </category>
  <size>
   S
  </size>
  <color>
   Фиолетовый
  </color>
  <material>
   Шерсть
  </material>
  <price>
   148357
  </price>
  <rating>
   1.37
  </rating>
  <reviews>
   263437
  </reviews>
  <new>
   -
  </new>
  <exclusive>
   no
  </exclusive>
 </clothing>
 <clothing>
  <id>
   861059738
  </id>
  <name>
   Asics Umbrellas C-6099
  </name>
  <category>
   Umbrellas
  </category>
  <size>
   L
  </size>
  <color>
   Голубой
  </color>
  <material>
   Хлопок
  </material>
  <price>
   332495
  </price>
  <rating>
   2.01
  </rating>
  <reviews>
   560480
  </reviews>
  <new>
   -
  </new>
  <exclusive>
   no
  </exclusive>
 </clothing>
 <clothing>
  <id>
   166996448
  </id>
  <name>
   PleinSport Jeans G-8195
  </name>
  <category>
   Jeans
  </category>
  <size>
   S
  </size>
  <color>
   Синий
  </color>
  <material>
   Лен
  </material>
  <price>
   649994
  </price>
  <rating>
   2.12
  </rating>
  <reviews>
   553361
  </reviews>
  <new>
   -
  </new>
 </clothing>
 <clothing>
  <id>
   879602359
  </id>
  <name>
   Asics Pants I-9774
  </name>
  <category>
   Pants
  </category>
  <size>
   XL
  </size>
  <color>
   Оранжевый
  </color>
  <material>
   Вискоза
  </material>
  <price>
   855558
  </price>
  <rating>
   1.96
  </rating>
  <reviews>
   529048
  </reviews>
  <new>
   +
  </new>
 </clothing>
 <clothing>
  <id>
   280793147
  </id>
  <name>
   New Balance Belts N-9549
  </name>
  <category>
   Belts
  </category>
  <size>
   XL
  </size>
  <color>
   Зеленый
  </color>
  <material>
   Шерсть
  </material>
  <price>
   690478
  </price>
  <rating>
   1.33
  </rating>
  <reviews>
   460956
  </reviews>
  <new>
   -
  </new>
  <exclusive>
   yes
  </exclusive>
 </clothing>
 <clothing>
  <id>
   389332448
  </id>
  <name>
   Converse Gloves J-8760
  </name>
  <category>
   Gloves
  </category>
  <size>
   XXL
  </size>
  <color>
   Голубой
  </color>
  <material>
   Вискоза
  </material>
  <price>
   952390
  </price>
  <rating>
   1.2
  </rating>
  <reviews>
   229824
  </reviews>
  <new>
   -
  </new>
  <exclusive>
   yes
  </exclusive>
 </clothing>
 <clothing>
  <id>
   990033865
  </id>
  <name>
   Under Armour Shirt U-7981
  </name>
  <category>
   Shirt
  </category>
  <size>
   S
  </size>
  <color>
   Голубой
  </color>
  <material>
   Вискоза
  </material>
  <price>
   929270
  </price>
  <rating>
   2.65
  </rating>
  <reviews>
   489322
  </reviews>
  <new>
   -
  </new>
  <sporty>
   no
  </sporty>
 </clothing>
 <clothing>
  <id>
   736453322
  </id>
  <name>
   Addidas Shoes U-9531
  </name>
  <category>
   Shoes
  </category>
  <size>
   M
  </size>
  <color>
   Синий
  </color>
  <material>
   Полиэстер
  </material>
  <price>
   324502
  </price>
  <rating>
   2.68
  </rating>
  <reviews>
   918650
  </reviews>
  <new>
   -
  </new>
  <sporty>
   yes
  </sporty>
 </clothing>
 <clothing>
  <id>
   218154184
  </id>
  <name>
   Vans Shirt J-3397
  </name>
  <category>
   Shirt
  </category>
  <size>
   S
  </size>
  <color>
   Желтый
  </color>
  <material>
   Кожа
  </material>
  <price>
   541131
  </price>
  <rating>
   3.32
  </rating>
  <reviews>
   618720
  </reviews>
  <exclusive>
   yes
  </exclusive>
  <sporty>
   no
  </sporty>
 </clothing>
 <clothing>
  <id>
   763459659
  </id>
  <name>
   Addidas Hat U-2168
  </name>
  <category>
   Hat
  </category>
  <size>
   L
  </size>
  <color>
   Оранжевый
  </color>
  <material>
   Шерсть
  </material>
  <price>
   771049
  </price>
  <rating>
   1.02
  </rating>
  <reviews>
   922343
  </reviews>
  <new>
   -
  </new>
  <exclusive>
   no
  </exclusive>
  <sporty>
   no
  </sporty>
 </clothing>
 <clothing>
  <id>
   800222643
  </id>
  <name>
   Under Armour Blouse W-3471
  </name>
  <category>
   Blouse
  </category>
  <size>
   XXL
  </size>
  <color>
   Красный
  </color>
  <material>
   Шелк
  </material>
  <price>
   269095
  </price>
  <rating>
   1.58
  </rating>
  <reviews>
   297312
  </reviews>
  <new>
   -
  </new>
 </clothing>
 <clothing>
  <id>
   670851327
  </id>
  <name>
   Asics Pants C-4026
  </name>
  <category>
   Pants
  </category>
  <size>
   M
  </size>
  <color>
   Фиолетовый
  </color>
  <material>
   Лен
  </material>
  <price>
   142640
  </price>
  <rating>
   2.34
  </rating>
  <reviews>
   527442
  </reviews>
  <new>
   -
  </new>
 </clothing>
 <clothing>
  <id>
   405089988
  </id>
  <name>
   PleinSport Pants B-3815
  </name>
  <category>
   Pants
  </category>
  <size>
   L
  </size>
  <color>
   Голубой
  </color>
  <material>
   Хлопок
  </material>
  <price>
   971113
  </price>
  <rating>
   3.01
  </rating>
  <reviews>
   589803
  </reviews>
  <new>
   -
  </new>
  <sporty>
   no
  </sporty>
 </clothing>
</clothing-items>
