<?xml version="1.0" encoding="utf-8"?>
<clothing-items>
 <clothing>
  <id>
   924695323
  </id>
  <name>
   Nike Handbags U-9706
  </name>
  <category>
   Handbags
  </category>
  <size>
   S
  </size>
  <color>
   Красный
  </color>
  <material>
   Лен
  </material>
  <price>
   765929
  </price>
  <rating>
   2.4
  </rating>
  <reviews>
   122170
  </reviews>
  <sporty>
   no
  </sporty>
 </clothing>
 <clothing>
  <id>
   968934498
  </id>
  <name>
   Brooks Hat V-3998
  </name>
  <category>
   Hat
  </category>
  <size>
   S
  </size>
  <color>
   Фиолетовый
  </color>
  <material>
   Нейлон
  </material>
  <price>
   474073
  </price>
  <rating>
   2.81
  </rating>
  <reviews>
   918434
  </reviews>
  <exclusive>
   no
  </exclusive>
  <sporty>
   no
  </sporty>
 </clothing>
 <clothing>
  <id>
   659135734
  </id>
  <name>
   Nike Handbags Q-4862
  </name>
  <category>
   Handbags
  </category>
  <size>
   M
  </size>
  <color>
   Красный
  </color>
  <material>
   Шелк
  </material>
  <price>
   995133
  </price>
  <rating>
   4.29
  </rating>
  <reviews>
   61595
  </reviews>
  <new>
   -
  </new>
  <sporty>
   no
  </sporty>
 </clothing>
 <clothing>
  <id>
   952607888
  </id>
  <name>
   Vans Sweater I-5195
  </name>
  <category>
   Sweater
  </category>
  <size>
   XXL
  </size>
  <color>
   Фиолетовый
  </color>
  <material>
   Шерсть
  </material>
  <price>
   584601
  </price>
  <rating>
   1.76
  </rating>
  <reviews>
   955703
  </reviews>
  <new>
   -
  </new>
  <exclusive>
   no
  </exclusive>
  <sporty>
   yes
  </sporty>
 </clothing>
 <clothing>
  <id>
   519065099
  </id>
  <name>
   Brooks Dress L-6858
  </name>
  <category>
   Dress
  </category>
  <size>
   XL
  </size>
  <color>
   Красный
  </color>
  <material>
   Нейлон
  </material>
  <price>
   881011
  </price>
  <rating>
   4.18
  </rating>
  <reviews>
   675322
  </reviews>
  <new>
   -
  </new>
  <exclusive>
   yes
  </exclusive>
 </clothing>
 <clothing>
  <id>
   312061880
  </id>
  <name>
   Under Armour Shirt R-4216
  </name>
  <category>
   Shirt
  </category>
  <size>
   M
  </size>
  <color>
   Желтый
  </color>
  <material>
   Шелк
  </material>
  <price>
   593614
  </price>
  <rating>
   2.0
  </rating>
  <reviews>
   178005
  </reviews>
  <exclusive>
   no
  </exclusive>
 </clothing>
 <clothing>
  <id>
   416154480
  </id>
  <name>
   Nike Dress H-5408
  </name>
  <category>
   Dress
  </category>
  <size>
   L
  </size>
  <color>
   Желтый
  </color>
  <material>
   Вискоза
  </material>
  <price>
   628747
  </price>
  <rating>
   3.97
  </rating>
  <reviews>
   531195
  </reviews>
 </clothing>
 <clothing>
  <id>
   757901981
  </id>
  <name>
   Lacoste Hat V-5521
  </name>
  <category>
   Hat
  </category>
  <size>
   M
  </size>
  <color>
   Фиолетовый
  </color>
  <material>
   Вискоза
  </material>
  <price>
   121205
  </price>
  <rating>
   2.18
  </rating>
  <reviews>
   736850
  </reviews>
  <new>
   -
  </new>
  <exclusive>
   yes
  </exclusive>
  <sporty>
   yes
  </sporty>
 </clothing>
 <clothing>
  <id>
   714644593
  </id>
  <name>
   Adidas Sweater E-2310
  </name>
  <category>
   Sweater
  </category>
  <size>
   L
  </size>
  <color>
   Зеленый
  </color>
  <material>
   Нейлон
  </material>
  <price>
   150646
  </price>
  <rating>
   3.46
  </rating>
  <reviews>
   403238
  </reviews>
  <new>
   +
  </new>
  <exclusive>
   no
  </exclusive>
 </clothing>
 <clothing>
  <id>
   502961579
  </id>
  <name>
   Addidas Jeans O-2823
  </name>
  <category>
   Jeans
  </category>
  <size>
   M
  </size>
  <color>
   Красный
  </color>
  <material>
   Вискоза
  </material>
  <price>
   822185
  </price>
  <rating>
   2.69
  </rating>
  <reviews>
   543056
  </reviews>
  <new>
   -
  </new>
  <sporty>
   no
  </sporty>
 </clothing>
 <clothing>
  <id>
   485014498
  </id>
  <name>
   Nike Shirt P-5608
  </name>
  <category>
   Shirt
  </category>
  <size>
   M
  </size>
  <color>
   Синий
  </color>
  <material>
   Хлопок
  </material>
  <price>
   125667
  </price>
  <rating>
   2.21
  </rating>
  <reviews>
   996923
  </reviews>
  <new>
   +
  </new>
  <sporty>
   yes
  </sporty>
 </clothing>
 <clothing>
  <id>
   251210976
  </id>
  <name>
   Reebok Pants C-5611
  </name>
  <category>
   Pants
  </category>
  <size>
   XXL
  </size>
  <color>
   Красный
  </color>
  <material>
   Хлопок
  </material>
  <price>
   616189
  </price>
  <rating>
   2.0
  </rating>
  <reviews>
   65176
  </reviews>
  <exclusive>
   yes
  </exclusive>
  <sporty>
   yes
  </sporty>
 </clothing>
 <clothing>
  <id>
   848885181
  </id>
  <name>
   Lacoste Sweater B-8514
  </name>
  <category>
   Sweater
  </category>
  <size>
   L
  </size>
  <color>
   Фиолетовый
  </color>
  <material>
   Нейлон
  </material>
  <price>
   952237
  </price>
  <rating>
   2.97
  </rating>
  <reviews>
   555955
  </reviews>
  <new>
   +
  </new>
 </clothing>
 <clothing>
  <id>
   315077465
  </id>
  <name>
   Puma Blouse A-2228
  </name>
  <category>
   Blouse
  </category>
  <size>
   L
  </size>
  <color>
   Фиолетовый
  </color>
  <material>
   Шелк
  </material>
  <price>
   271194
  </price>
  <rating>
   2.44
  </rating>
  <reviews>
   71254
  </reviews>
  <new>
   -
  </new>
  <exclusive>
   no
  </exclusive>
 </clothing>
 <clothing>
  <id>
   786222531
  </id>
  <name>
   Under Armour Belts M-3765
  </name>
  <category>
   Belts
  </category>
  <size>
   L
  </size>
  <color>
   Голубой
  </color>
  <material>
   Шелк
  </material>
  <price>
   660021
  </price>
  <rating>
   3.16
  </rating>
  <reviews>
   466212
  </reviews>
  <new>
   +
  </new>
  <exclusive>
   no
  </exclusive>
 </clothing>
 <clothing>
  <id>
   322515155
  </id>
  <name>
   Puma Pants O-7841
  </name>
  <category>
   Pants
  </category>
  <size>
   S
  </size>
  <color>
   Фиолетовый
  </color>
  <material>
   Полиэстер
  </material>
  <price>
   265608
  </price>
  <rating>
   1.9
  </rating>
  <reviews>
   516284
  </reviews>
  <exclusive>
   no
  </exclusive>
  <sporty>
   yes
  </sporty>
 </clothing>
 <clothing>
  <id>
   572103868
  </id>
  <name>
   PleinSport T-shirt U-5896
  </name>
  <category>
   T-shirt
  </category>
  <size>
   M
  </size>
  <color>
   Фиолетовый
  </color>
  <material>
   Нейлон
  </material>
  <price>
   577086
  </price>
  <rating>
   3.55
  </rating>
  <reviews>
   427621
  </reviews>
  <exclusive>
   no
  </exclusive>
 </clothing>
 <clothing>
  <id>
   859660032
  </id>
  <name>
   Brooks Sweater C-5764
  </name>
  <category>
   Sweater
  </category>
  <size>
   L
  </size>
  <color>
   Красный
  </color>
  <material>
   Лен
  </material>
  <price>
   115412
  </price>
  <rating>
   2.95
  </rating>
  <reviews>
   783869
  </reviews>
  <exclusive>
   yes
  </exclusive>
 </clothing>
 <clothing>
  <id>
   551487256
  </id>
  <name>
   Under Armour Jeans R-5912
  </name>
  <category>
   Jeans
  </category>
  <size>
   S
  </size>
  <color>
   Зеленый
  </color>
  <material>
   Шерсть
  </material>
  <price>
   401616
  </price>
  <rating>
   4.39
  </rating>
  <reviews>
   245346
  </reviews>
 </clothing>
 <clothing>
  <id>
   305147188
  </id>
  <name>
   Puma Blouse H-6643
  </name>
  <category>
   Blouse
  </category>
  <size>
   S
  </size>
  <color>
   Зеленый
  </color>
  <material>
   Хлопок
  </material>
  <price>
   405785
  </price>
  <rating>
   2.75
  </rating>
  <reviews>
   566290
  </reviews>
  <new>
   -
  </new>
  <exclusive>
   yes
  </exclusive>
  <sporty>
   no
  </sporty>
 </clothing>
 <clothing>
  <id>
   298462003
  </id>
  <name>
   Addidas T-shirt R-2335
  </name>
  <category>
   T-shirt
  </category>
  <size>
   XXL
  </size>
  <color>
   Оранжевый
  </color>
  <material>
   Шелк
  </material>
  <price>
   293425
  </price>
  <rating>
   4.61
  </rating>
  <reviews>
   513356
  </reviews>
  <new>
   +
  </new>
 </clothing>
 <clothing>
  <id>
   700421278
  </id>
  <name>
   PleinSport Shoes W-1129
  </name>
  <category>
   Shoes
  </category>
  <size>
   L
  </size>
  <color>
   Фиолетовый
  </color>
  <material>
   Хлопок
  </material>
  <price>
   672304
  </price>
  <rating>
   2.7
  </rating>
  <reviews>
   873121
  </reviews>
  <new>
   -
  </new>
  <exclusive>
   no
  </exclusive>
 </clothing>
 <clothing>
  <id>
   439030475
  </id>
  <name>
   DC Pants F-8860
  </name>
  <category>
   Pants
  </category>
  <size>
   XL
  </size>
  <color>
   Синий
  </color>
  <material>
   Шелк
  </material>
  <price>
   881475
  </price>
  <rating>
   4.0
  </rating>
  <reviews>
   680731
  </reviews>
  <new>
   -
  </new>
  <sporty>
   yes
  </sporty>
 </clothing>
 <clothing>
  <id>
   183939066
  </id>
  <name>
   Converse Sweater V-1038
  </name>
  <category>
   Sweater
  </category>
  <size>
   L
  </size>
  <color>
   Желтый
  </color>
  <material>
   Хлопок
  </material>
  <price>
   333143
  </price>
  <rating>
   2.28
  </rating>
  <reviews>
   256518
  </reviews>
  <new>
   -
  </new>
  <sporty>
   yes
  </sporty>
 </clothing>
 <clothing>
  <id>
   854886997
  </id>
  <name>
   Vans Pants K-4960
  </name>
  <category>
   Pants
  </category>
  <size>
   XXL
  </size>
  <color>
   Оранжевый
  </color>
  <material>
   Нейлон
  </material>
  <price>
   964925
  </price>
  <rating>
   2.09
  </rating>
  <reviews>
   486529
  </reviews>
  <exclusive>
   yes
  </exclusive>
  <sporty>
   no
  </sporty>
 </clothing>
 <clothing>
  <id>
   589477270
  </id>
  <name>
   Converse Shoes Y-9968
  </name>
  <category>
   Shoes
  </category>
  <size>
   L
  </size>
  <color>
   Оранжевый
  </color>
  <material>
   Шерсть
  </material>
  <price>
   310297
  </price>
  <rating>
   2.99
  </rating>
  <reviews>
   333551
  </reviews>
  <new>
   -
  </new>
  <exclusive>
   yes
  </exclusive>
 </clothing>
 <clothing>
  <id>
   499536929
  </id>
  <name>
   PleinSport Hat V-6661
  </name>
  <category>
   Hat
  </category>
  <size>
   XL
  </size>
  <color>
   Синий
  </color>
  <material>
   Полиэстер
  </material>
  <price>
   640426
  </price>
  <rating>
   1.1
  </rating>
  <reviews>
   210511
  </reviews>
  <new>
   +
  </new>
 </clothing>
 <clothing>
  <id>
   173130388
  </id>
  <name>
   Converse Hat M-4370
  </name>
  <category>
   Hat
  </category>
  <size>
   M
  </size>
  <color>
   Голубой
  </color>
  <material>
   Кожа
  </material>
  <price>
   962507
  </price>
  <rating>
   1.95
  </rating>
  <reviews>
   777938
  </reviews>
  <new>
   -
  </new>
 </clothing>
 <clothing>
  <id>
   924778439
  </id>
  <name>
   Nike Skirt E-3257
  </name>
  <category>
   Skirt
  </category>
  <size>
   XXL
  </size>
  <color>
   Красный
  </color>
  <material>
   Кожа
  </material>
  <price>
   962143
  </price>
  <rating>
   1.16
  </rating>
  <reviews>
   929489
  </reviews>
  <exclusive>
   yes
  </exclusive>
 </clothing>
 <clothing>
  <id>
   869846687
  </id>
  <name>
   New Balance Shoes N-3150
  </name>
  <category>
   Shoes
  </category>
  <size>
   XXL
  </size>
  <color>
   Синий
  </color>
  <material>
   Полиэстер
  </material>
  <price>
   137291
  </price>
  <rating>
   4.7
  </rating>
  <reviews>
   462438
  </reviews>
  <new>
   +
  </new>
  <sporty>
   no
  </sporty>
 </clothing>
 <clothing>
  <id>
   336085043
  </id>
  <name>
   Under Armour Jacket J-6622
  </name>
  <category>
   Jacket
  </category>
  <size>
   XL
  </size>
  <color>
   Фиолетовый
  </color>
  <material>
   Вискоза
  </material>
  <price>
   547505
  </price>
  <rating>
   1.13
  </rating>
  <reviews>
   729624
  </reviews>
  <new>
   -
  </new>
  <sporty>
   no
  </sporty>
 </clothing>
</clothing-items>
